MANIFEST.in
README.md
setup.py
instagram/__init__.py
instagram/client.py
instagram/decorators.py
instagram/exceptions.py
instagram_python_lib.egg-info/PKG-INFO
instagram_python_lib.egg-info/SOURCES.txt
instagram_python_lib.egg-info/dependency_links.txt
instagram_python_lib.egg-info/not-zip-safe
instagram_python_lib.egg-info/requires.txt
instagram_python_lib.egg-info/top_level.txt