Metadata-Version: 1.0
Name: instagram-python-lib
Version: 0.1.2
Summary: API wrapper for Instagram written in Python
Home-page: https://github.com/GearPlug/instagram-python
Author: Miguel Ferrer
Author-email: ingferrermiguel@gmail.com
License: GPL
Platform: UNKNOWN
